cppvector/__init__.py
cppvector/vector.py
cppvector_jediz-0.1.1.dist-info/METADATA
cppvector_jediz-0.1.1.dist-info/WHEEL
cppvector_jediz-0.1.1.dist-info/top_level.txt
cppvector_jediz-0.1.1.dist-info/RECORD
