Metadata-Version: 2.4
Name: cppvector-jediz
Version: 0.1.1
Summary: A C++ style vector implementation for Python
Home-page: https://github.com/JedizLaPulga/lapython
Author: Your Name
Author-email: JedizLaPulga <jedizlapulga@gmail.com>
License: MIT
Project-URL: Homepage, https://github.com/JedizLaPulga/lapython
Project-URL: Bug Tracker, https://github.com/JedizLaPulga/lapython/issues
Classifier: Development Status :: 3 - Alpha
Classifier: Intended Audience :: Developers
Classifier: Topic :: Software Development :: Libraries
Classifier: License :: OSI Approved :: MIT License
Classifier: Programming Language :: Python :: 3
Classifier: Programming Language :: Python :: 3.7
Classifier: Programming Language :: Python :: 3.8
Classifier: Programming Language :: Python :: 3.9
Classifier: Programming Language :: Python :: 3.10
Classifier: Programming Language :: Python :: 3.11
Requires-Python: >=3.7
Dynamic: author
Dynamic: home-page
Dynamic: requires-python
